recnetlogin/__init__.py
recnetlogin/client.py
recnetlogin/exceptions.py
recnetlogin-0.2.0.dist-info/LICENSE.txt
recnetlogin-0.2.0.dist-info/METADATA
recnetlogin-0.2.0.dist-info/WHEEL
recnetlogin-0.2.0.dist-info/top_level.txt
recnetlogin-0.2.0.dist-info/RECORD
