Metadata-Version: 2.1
Name: recnetlogin
Version: 0.2.0
Summary: RecNetLogin is a Python library that lets you to acquire your RecNet access token and more!
Author: Jegarde
Project-URL: Homepage, https://github.com/Jegarde/RecNet-Login
Project-URL: Bug Tracker, https://github.com/Jegarde/RecNet-Login/issues
Classifier: Programming Language :: Python :: 3
Classifier: License :: OSI Approved :: MIT License
Classifier: Operating System :: OS Independent
Requires-Python: >=3.8
License-File: LICENSE.txt
Requires-Dist: PyJWT==2.7.0
Requires-Dist: httpx>=0.24.1
Requires-Dist: python-dotenv==1.0.0
